pymeterreader/__init__.py
pymeterreader/meter_reader.py
pymeterreader/test_meter_reader.py
pymeterreader/core/__init__.py
pymeterreader/core/channel_description.py
pymeterreader/core/channel_upload_info.py
pymeterreader/core/meter_reader_node.py
pymeterreader/core/meter_reader_task.py
pymeterreader/device_lib/__init__.py
pymeterreader/device_lib/base.py
pymeterreader/device_lib/common.py
pymeterreader/device_lib/meter_plain.py
pymeterreader/device_lib/meter_sml.py
pymeterreader/device_lib/sensor_bme280.py
pymeterreader/device_lib/serial_reader.py
pymeterreader/device_lib/test_base.py
pymeterreader/device_lib/test_meter.py
pymeterreader/device_lib/test_meter_plain.py
pymeterreader/device_lib/test_meter_sml.py
pymeterreader/device_lib/test_sensor_bme280.py
pymeterreader/gateway/__init__.py
pymeterreader/gateway/basegateway.py
pymeterreader/gateway/debug.py
pymeterreader/gateway/mqtt.py
pymeterreader/gateway/volkszaehler.py
pymeterreader/metrics/__init__.py
pymeterreader/metrics/metrics_collector.py
pymeterreader/metrics/prefix.py
pymeterreader/wizard/__init__.py
pymeterreader/wizard/detector.py
pymeterreader/wizard/generator.py
pymeterreader/wizard/ncui.py
pymeterreader-0.3.0.data/data/example_configuration.yaml
pymeterreader-0.3.0.data/data/requirements.txt
pymeterreader-0.3.0.dist-info/LICENSE
pymeterreader-0.3.0.dist-info/METADATA
pymeterreader-0.3.0.dist-info/WHEEL
pymeterreader-0.3.0.dist-info/entry_points.txt
pymeterreader-0.3.0.dist-info/top_level.txt
pymeterreader-0.3.0.dist-info/RECORD
